wagtailimportexport/.DS_Store
wagtailimportexport/__init__.py
wagtailimportexport/admin_urls.py
wagtailimportexport/apps.py
wagtailimportexport/compat.py
wagtailimportexport/exporting.py
wagtailimportexport/forms.py
wagtailimportexport/importing.py
wagtailimportexport/urls.py
wagtailimportexport/views.py
wagtailimportexport/wagtail_hooks.py
wagtailimportexport/templates/wagtailimportexport/export_to_file.html
wagtailimportexport/templates/wagtailimportexport/import_from_api.html
wagtailimportexport/templates/wagtailimportexport/import_from_file.html
wagtailimportexport/templates/wagtailimportexport/index.html
wagtailimportexport/tests/__init__.py
wagtailimportexport/tests/test_functions.py
wagtail_import_export_updated-0.1.5.dist-info/LICENSE
wagtail_import_export_updated-0.1.5.dist-info/METADATA
wagtail_import_export_updated-0.1.5.dist-info/WHEEL
wagtail_import_export_updated-0.1.5.dist-info/top_level.txt
wagtail_import_export_updated-0.1.5.dist-info/RECORD
