Metadata-Version: 2.1
Name: wagtail-import-export-updated
Version: 0.1.5
Summary: Import/Export for Wagtail CMS pages, images and documents.
Home-page: https://github.com/besarbertasholli/wagtail-import-export-updated
Author: Besarber Tasholli
Author-email: besarbertasholli@hotmail.com
License: BSD
Classifier: Development Status :: 5 - Production/Stable
Classifier: Environment :: Web Environment
Classifier: Intended Audience :: Developers
Classifier: License :: OSI Approved :: BSD License
Classifier: Operating System :: OS Independent
Classifier: Programming Language :: Python
Classifier: Programming Language :: Python :: 3
Classifier: Framework :: Django
License-File: LICENSE
